ringflasher.v
`timescale 1ps/1ps
module ringflasher (
    input clk,
    input rst_n,
    input flick,
    output reg [15:0] led
);
    integer N;
    integer i;
    reg [1:0] operation;

    parameter IDLE = 2'b00;
    parameter UP = 2'b01;
    parameter DOWN = 2'b10;
    parameter KICKBACK = 2'b11;

    parameter INIT          = 7'b0000001;
    parameter ON_0_TO_15    = 7'b0000010;
    parameter OFF_15_TO_5   = 7'b0000100;
    parameter ON_5_TO_10    = 7'b0001000;
    parameter OFF_10_TO_0   = 7'b0010000;
    parameter ON_0_TO_5     = 7'b0100000;
    parameter OFF_5_TO_0    = 7'b1000000;

    parameter SIZE = 7 ;
    reg [SIZE - 1:0] state;
    reg [SIZE - 1:0] next_state;

    //Change_state block
    always@(posedge clk or negedge rst_n)begin
        if(!rst_n)begin
            state <= INIT;
        end
        else begin
            state <= next_state;
        end
    end

    //Logic block
    always@(*)begin
        operation = IDLE;

        case (state)
        INIT: begin
                operation = IDLE;
            end

        ON_0_TO_15: begin
            if(N < 15) 
                operation = UP;
            else 
                operation = DOWN;
        end

        OFF_15_TO_5:begin
            if(flick && (N == 5))
                operation = KICKBACK;
            else if (N > 5)
                operation = DOWN;
            else 
                operation = UP;
        end

        ON_5_TO_10:begin
            if(N < 10)
                operation = UP;
            else
                operation = DOWN;
        end

        OFF_10_TO_0:begin
            if(flick && (N == 0))
                operation = KICKBACK;
            else if(N > 0)
                operation = DOWN;
            else 
                operation = UP;
        end

        ON_0_TO_5:begin
            if(N < 5)
                operation = UP;
            else 
                operation = DOWN;
        end

        OFF_5_TO_0:begin
            if(N > 0)
                operation = DOWN;
            else    
                operation = IDLE;
        end
            default: operation = IDLE;
        endcase
    end


    //Operation block
    always@(posedge clk or negedge rst_n)begin
        if (!rst_n) begin
            N <= 0;
        end 
        else begin
        if (operation == UP)begin
            if(N < 15)
                N<=N + 1;
            else
                N <= 15;
            end 
        else if (operation == DOWN || operation == KICKBACK)begin
            if(N > 0)
                N <= N - 1;
            else 
                N <= 0;
            end
        end
    end

    //FSM block
    always@(*)begin
        case (state)
            INIT:begin
                if(flick)
                    next_state = ON_0_TO_15; 
                else
                    next_state = INIT;
            end

            ON_0_TO_15: begin
                if(operation == UP)
                    next_state = ON_0_TO_15;
                else begin
                    next_state = OFF_15_TO_5;
                end
            end

            OFF_15_TO_5: begin
                if(operation == DOWN || operation == KICKBACK)
                    next_state = OFF_15_TO_5;
                else
                    next_state = ON_5_TO_10;
            end

            ON_5_TO_10: begin
                if(operation == UP)
                    next_state = ON_5_TO_10;
                else
                    next_state = OFF_10_TO_0;
            end

            OFF_10_TO_0: begin
                if(operation == DOWN || operation == KICKBACK)
                    next_state = OFF_10_TO_0;
                else
                    next_state = ON_0_TO_5;
            end

            ON_0_TO_5: begin
                if(operation == UP)
                    next_state = ON_0_TO_5;
                else
                    next_state = OFF_5_TO_0;
            end

            OFF_5_TO_0:begin
                if(operation == DOWN)
                    next_state = OFF_5_TO_0;
                else
                    next_state = INIT;
            end
            default: begin
                next_state = INIT;
            end
        endcase
    end

    //Decode
    always @(*) begin
        led = 16'b0;
        if(state != INIT)begin
        for (i = 0; i < 16 ; i = i + 1) begin
                if((N >=0) && (N < 16) && (i <= N))
                    led[i] = 1'b1;
                else
                    led[i] = 1'b0;
            end
        end
    end
endmodule

//UP: N = N + 1
//DOWN: N = N - 1
//KICKBACK: N = N - 1

tb_ringflasher.v
`timescale 1ps/1ps

module tb_ringflasher;

    reg clk;
    reg rst_n;
    reg flick;
    wire [15:0] led;

    ringflasher dut (
        .clk(clk),
        .rst_n(rst_n),
        .flick(flick),
        .led(led)
    );

    // Clock generation

    initial begin
        clk = 0;
        forever #5 clk = ~clk;   // 10ps period
    end

    // Dump waveform

    initial begin
        $dumpfile("wave.vcd");
        $dumpvars(0, tb_ringflasher.clk);
        $dumpvars(0, tb_ringflasher.rst_n);
        $dumpvars(0, tb_ringflasher.flick);
        $dumpvars(0, tb_ringflasher.led);
        $dumpvars(0, tb_ringflasher.dut.N);
        $dumpvars(0, tb_ringflasher.dut.state);
        $dumpvars(0, tb_ringflasher.dut.operation);
    end

    // Helpers

    task wait_posedge;
        input integer n;
        integer k;
        begin
            for (k = 0; k < n; k = k + 1)
                @(posedge clk);
        end
    endtask

    task pulse_flick_1clk;
        begin
            flick = 1'b1;
            @(posedge clk);
            #1;
            flick = 1'b0;
        end
    endtask

    task do_reset;
        begin
            rst_n = 1'b0;
            flick = 1'b0;
            wait_posedge(2);
            #1;
            rst_n = 1'b1;
        end
    endtask

    function [15:0] expected_led_from_n;
        input integer n;
        integer j;
        begin
            expected_led_from_n = 16'b0;
            if (n >= 0 && n < 16) begin
                for (j = 0; j < 16; j = j + 1) begin
                    if (j <= n)
                        expected_led_from_n[j] = 1'b1;
                    else
                        expected_led_from_n[j] = 1'b0;
                end
            end
        end
    endfunction

    task check_led;
        input [15:0] exp;
        input [255:0] msg;
        begin
            #1;
            if (led !== exp) begin
                $display("FAIL @%0t : %s | expected=%h got=%h", $time, msg, exp, led);
                $stop;
            end
            else begin
                $display("PASS @%0t : %s | led=%h", $time, msg, led);
            end
        end
    endtask

    task check_state;
        input [6:0] exp_state;
        input [255:0] msg;
        begin
            #1;
            if (dut.state !== exp_state) begin
                $display("FAIL @%0t : %s | expected state=%b got=%b", $time, msg, exp_state, dut.state);
                $stop;
            end
            else begin
                $display("PASS @%0t : %s | state=%b", $time, msg, dut.state);
            end
        end
    endtask

    // Main test

    initial begin
        rst_n = 1'b1;
        flick = 1'b0;

        // CASE 1: Reset -> INIT -> all OFF

        do_reset();
        check_state(dut.INIT, "after reset, state = INIT");
        check_led(16'h0000, "after reset, led all OFF");

        // CASE 2: Stay in INIT while flick=0

        wait_posedge(3);
        check_state(dut.INIT, "stay INIT when flick=0");
        check_led(16'h0000, "stay OFF when flick=0");

        // CASE 3: Start operating when flick is ACTIVE
 
        pulse_flick_1clk();
        wait_posedge(1);
        check_state(dut.ON_0_TO_15, "leave INIT and enter ON_0_TO_15");

        // code hiện tại của bạn sẽ bắt đầu với N=0 rồi tăng dần
        check_led(expected_led_from_n(dut.N), "LED pattern matches N in ON_0_TO_15");

        // CASE 4: Reach top of ON_0_TO_15

        while (dut.state == dut.ON_0_TO_15)
            @(posedge clk);

        #1;
        check_state(dut.OFF_15_TO_5, "transition ON_0_TO_15 -> OFF_15_TO_5");
        check_led(expected_led_from_n(dut.N), "LED pattern valid in OFF_15_TO_5");

        // CASE 5: Normal OFF_15_TO_5 without kickback

        while (dut.state == dut.OFF_15_TO_5 && dut.N > 5)
            @(posedge clk);

        @(posedge clk);
        #1;
        check_state(dut.ON_5_TO_10, "transition OFF_15_TO_5 -> ON_5_TO_10 (normal)");
        check_led(expected_led_from_n(dut.N), "LED pattern valid in ON_5_TO_10");

        // CASE 6: Reach OFF_10_TO_0 normally

        while (dut.state == dut.ON_5_TO_10)
            @(posedge clk);

        #1;
        check_state(dut.OFF_10_TO_0, "transition ON_5_TO_10 -> OFF_10_TO_0");
        check_led(expected_led_from_n(dut.N), "LED pattern valid in OFF_10_TO_0");

        // CASE 7: Normal OFF_10_TO_0 without kickback

        while (dut.state == dut.OFF_10_TO_0 && dut.N > 0)
            @(posedge clk);

        @(posedge clk);
        #1;
        check_state(dut.ON_0_TO_5, "transition OFF_10_TO_0 -> ON_0_TO_5 (normal)");
        check_led(expected_led_from_n(dut.N), "LED pattern valid in ON_0_TO_5");

        // CASE 8: Reach OFF_5_TO_0 normally

        while (dut.state == dut.ON_0_TO_5)
            @(posedge clk);

        #1;
        check_state(dut.OFF_5_TO_0, "transition ON_0_TO_5 -> OFF_5_TO_0");
        check_led(expected_led_from_n(dut.N), "LED pattern valid in OFF_5_TO_0");

        // CASE 9: Final OFF state returns to INIT
        // no kickback allowed here

        while (dut.state == dut.OFF_5_TO_0 && dut.N > 0)
            @(posedge clk);

        @(posedge clk);
        #1;
        check_state(dut.INIT, "transition OFF_5_TO_0 -> INIT");
        check_led(16'h0000, "back to all OFF at INIT");

        // KICKBACK TEST 1: kickback at N=5 in OFF_15_TO_5

        $display("------ KICKBACK TEST AT 5 ------");
        do_reset();
        pulse_flick_1clk();

        while (dut.state != dut.OFF_15_TO_5)
            @(posedge clk);

        while (!(dut.state == dut.OFF_15_TO_5 && dut.N == 5))
            @(posedge clk);

        flick = 1'b1;
        @(posedge clk);
        #1;
        flick = 1'b0;

        // do code của bạn giữ state khi KICKBACK
        check_state(dut.OFF_15_TO_5, "kickback at 5 repeats OFF_15_TO_5");
        check_led(expected_led_from_n(dut.N), "LED pattern valid after kickback at 5");

        // KICKBACK TEST 2: kickback at N=0 in OFF_10_TO_0

        $display("------ KICKBACK TEST AT 0 ------");
        do_reset();
        pulse_flick_1clk();

        while (dut.state != dut.OFF_10_TO_0)
            @(posedge clk);

        while (!(dut.state == dut.OFF_10_TO_0 && dut.N == 0))
            @(posedge clk);

        flick = 1'b1;
        @(posedge clk);
        #1;
        flick = 1'b0;

        check_state(dut.OFF_10_TO_0, "kickback at 0 repeats OFF_10_TO_0");
        check_led(expected_led_from_n(dut.N), "LED pattern valid after kickback at 0");

        // FINAL STATE NO KICKBACK
    
        $display("------ FINAL STATE NO KICKBACK ------");
        do_reset();
        pulse_flick_1clk();

        while (dut.state != dut.OFF_5_TO_0)
            @(posedge clk);

        while (!(dut.state == dut.OFF_5_TO_0 && dut.N == 0))
            @(posedge clk);

        flick = 1'b1;
        @(posedge clk);
        #1;
        flick = 1'b0;

        check_state(dut.INIT, "OFF_5_TO_0 is final state, no kickback, must return INIT");
        check_led(16'h0000, "final state returns to all OFF");

        $display("==========================================");
        $display("ALL TESTS PASSED");
        $display("==========================================");
        $finish;
    end

endmodule

wave.vcd
$date
	Sun Mar 29 17:07:29 2026
$end
$version
	Icarus Verilog
$end
$timescale
	1ps
$end
$scope module tb_ringflasher $end
$var reg 1 ! clk $end
$upscope $end
$scope module tb_ringflasher $end
$var reg 1 " rst_n $end
$upscope $end
$scope module tb_ringflasher $end
$var reg 1 # flick $end
$upscope $end
$scope module tb_ringflasher $end
$var wire 16 $ led [15:0] $end
$upscope $end
$scope module tb_ringflasher $end
$scope module dut $end
$var integer 32 % N [31:0] $end
$upscope $end
$upscope $end
$scope module tb_ringflasher $end
$scope module dut $end
$var reg 7 & state [6:0] $end
$upscope $end
$upscope $end
$scope module tb_ringflasher $end
$scope module dut $end
$var reg 2 ' operation [1:0] $end
$upscope $end
$upscope $end
$enddefinitions $end
#0
$dumpvars
b0 '
b1 &
b0 %
b0 $
0#
0"
0!
$end
#5
1!
#10
0!
#15
1!
#16
1"
#20
0!
#25
1!
#30
0!
#35
1!
#40
0!
#45
1!
#47
1#
#50
0!
#55
b1 $
b1 '
b10 &
1!
#56
b1 '
0#
#60
0!
#65
b11 $
b1 '
b1 %
1!
#70
0!
#75
b111 $
b1 '
b10 %
1!
#80
0!
#85
b1111 $
b1 '
b11 %
1!
#90
0!
#95
b11111 $
b1 '
b100 %
1!
#100
0!
#105
b111111 $
b1 '
b101 %
1!
#110
0!
#115
b1111111 $
b1 '
b110 %
1!
#120
0!
#125
b11111111 $
b1 '
b111 %
1!
#130
0!
#135
b111111111 $
b1 '
b1000 %
1!
#140
0!
#145
b1111111111 $
b1 '
b1001 %
1!
#150
0!
#155
b11111111111 $
b1 '
b1010 %
1!
#160
0!
#165
b111111111111 $
b1 '
b1011 %
1!
#170
0!
#175
b1111111111111 $
b1 '
b1100 %
1!
#180
0!
#185
b11111111111111 $
b1 '
b1101 %
1!
#190
0!
#195
b111111111111111 $
b1 '
b1110 %
1!
#200
0!
#205
b1111111111111111 $
b10 '
b1111 %
1!
#210
0!
#215
b111111111111111 $
b10 '
b100 &
b1110 %
1!
#220
0!
#225
b11111111111111 $
b10 '
b1101 %
1!
#230
0!
#235
b1111111111111 $
b10 '
b1100 %
1!
#240
0!
#245
b111111111111 $
b10 '
b1011 %
1!
#250
0!
#255
b11111111111 $
b10 '
b1010 %
1!
#260
0!
#265
b1111111111 $
b10 '
b1001 %
1!
#270
0!
#275
b111111111 $
b10 '
b1000 %
1!
#280
0!
#285
b11111111 $
b10 '
b111 %
1!
#290
0!
#295
b1111111 $
b10 '
b110 %
1!
#300
0!
#305
b111111 $
b1 '
b101 %
1!
#310
0!
#315
b1111111 $
b1 '
b1000 &
b110 %
1!
#320
0!
#325
b11111111 $
b1 '
b111 %
1!
#330
0!
#335
b111111111 $
b1 '
b1000 %
1!
#340
0!
#345
b1111111111 $
b1 '
b1001 %
1!
#350
0!
#355
b11111111111 $
b10 '
b1010 %
1!
#360
0!
#365
b1111111111 $
b10 '
b1001 %
b10000 &
1!
#370
0!
#375
b111111111 $
b10 '
b1000 %
1!
#380
0!
#385
b11111111 $
b10 '
b111 %
1!
#390
0!
#395
b1111111 $
b10 '
b110 %
1!
#400
0!
#405
b111111 $
b10 '
b101 %
1!
#410
0!
#415
b11111 $
b10 '
b100 %
1!
#420
0!
#425
b1111 $
b10 '
b11 %
1!
#430
0!
#435
b111 $
b10 '
b10 %
1!
#440
0!
#445
b11 $
b10 '
b1 %
1!
#450
0!
#455
b1 $
b1 '
b0 %
1!
#460
0!
#465
b11 $
b1 '
b1 %
b100000 &
1!
#470
0!
#475
b111 $
b1 '
b10 %
1!
#480
0!
#485
b1111 $
b1 '
b11 %
1!
#490
0!
#495
b11111 $
b1 '
b100 %
1!
#500
0!
#505
b111111 $
b10 '
b101 %
1!
#510
0!
#515
b11111 $
b10 '
b1000000 &
b100 %
1!
#520
0!
#525
b1111 $
b10 '
b11 %
1!
#530
0!
#535
b111 $
b10 '
b10 %
1!
#540
0!
#545
b11 $
b10 '
b1 %
1!
#550
0!
#555
b1 $
b0 '
b0 %
1!
#560
0!
#565
b0 $
b1 &
1!
#570
0!
#575
1!
#578
0"
#580
0!
#585
1!
#590
0!
#595
1!
#596
1#
1"
#600
0!
#605
b1 $
b1 '
b10 &
1!
#606
b1 '
0#
#610
0!
#615
b11 $
b1 '
b1 %
1!
#620
0!
#625
b111 $
b1 '
b10 %
1!
#630
0!
#635
b1111 $
b1 '
b11 %
1!
#640
0!
#645
b11111 $
b1 '
b100 %
1!
#650
0!
#655
b111111 $
b1 '
b101 %
1!
#660
0!
#665
b1111111 $
b1 '
b110 %
1!
#670
0!
#675
b11111111 $
b1 '
b111 %
1!
#680
0!
#685
b111111111 $
b1 '
b1000 %
1!
#690
0!
#695
b1111111111 $
b1 '
b1001 %
1!
#700
0!
#705
b11111111111 $
b1 '
b1010 %
1!
#710
0!
#715
b111111111111 $
b1 '
b1011 %
1!
#720
0!
#725
b1111111111111 $
b1 '
b1100 %
1!
#730
0!
#735
b11111111111111 $
b1 '
b1101 %
1!
#740
0!
#745
b111111111111111 $
b1 '
b1110 %
1!
#750
0!
#755
b1111111111111111 $
b10 '
b1111 %
1!
#760
0!
#765
b111111111111111 $
b10 '
b100 &
b1110 %
1!
#770
0!
#775
b11111111111111 $
b10 '
b1101 %
1!
#780
0!
#785
b1111111111111 $
b10 '
b1100 %
1!
#790
0!
#795
b111111111111 $
b10 '
b1011 %
1!
#800
0!
#805
b11111111111 $
b10 '
b1010 %
1!
#810
0!
#815
b1111111111 $
b10 '
b1001 %
1!
#820
0!
#825
b111111111 $
b10 '
b1000 %
1!
#830
0!
#835
b11111111 $
b10 '
b111 %
1!
#840
0!
#845
b1111111 $
b10 '
b110 %
1!
#850
0!
#855
b111111 $
b1 '
b101 %
1!
#860
0!
#865
b1111111 $
b1000 &
b110 %
b1 '
1#
1!
#870
0!
#875
b11111111 $
b1 '
b111 %
1!
#876
b1 '
0#
